AoikImportUtil-0.3.0.dist-info/METADATA
AoikImportUtil-0.3.0.dist-info/RECORD
AoikImportUtil-0.3.0.dist-info/WHEEL
AoikImportUtil-0.3.0.dist-info/top_level.txt
aoikimportutil/__init__.py
aoikimportutil/aoikimportutil.py
